Metadata-Version: 2.1
Name: baytune
Version: 0.5.0
Summary: Bayesian Tuning and Bandits
Author-email: MIT Data to AI Lab <dailabmit@mit.edu>
Maintainer-email: MIT Data to AI Lab <dailabmit@mit.edu>
License: MIT License
Project-URL: Source Code, https://github.com/MLBazaar/BTB/
Project-URL: Issue Tracker, https://github.com/MLBazaar/BTB/issues
Project-URL: Twitter, https://twitter.com/lab_dai
Keywords: data science,machine learning,hyperparameters,tuning,classification
Classifier: Development Status :: 2 - Pre-Alpha
Classifier: Intended Audience :: Science/Research
Classifier: Intended Audience :: Developers
Classifier: Topic :: Software Development
Classifier: Topic :: Scientific/Engineering
Classifier: Programming Language :: Python
Classifier: Programming Language :: Python :: 3
Classifier: Programming Language :: Python :: 3.8
Classifier: Programming Language :: Python :: 3.9
Classifier: Programming Language :: Python :: 3.10
Classifier: Programming Language :: Python :: 3.11
Classifier: Operating System :: Microsoft :: Windows
Classifier: Operating System :: POSIX
Classifier: Operating System :: Unix
Classifier: Operating System :: MacOS
Classifier: License :: OSI Approved :: MIT License
Classifier: Natural Language :: English
Requires-Python: <4,>=3.8
Provides-Extra: test
Provides-Extra: dev
Provides-Extra: docs
License-File: LICENSE
